odoo/addons/l10n_es_aeat_mod111/README.rst
odoo/addons/l10n_es_aeat_mod111/__init__.py
odoo/addons/l10n_es_aeat_mod111/__manifest__.py
odoo/addons/l10n_es_aeat_mod111/data/aeat_export_mod111_data.xml
odoo/addons/l10n_es_aeat_mod111/data/l10n.es.aeat.map.tax.csv
odoo/addons/l10n_es_aeat_mod111/data/l10n.es.aeat.map.tax.line.csv
odoo/addons/l10n_es_aeat_mod111/data/l10n.es.aeat.map.tax.line.tax.csv
odoo/addons/l10n_es_aeat_mod111/docs/dr111e16v17.xls
odoo/addons/l10n_es_aeat_mod111/i18n/bg.po
odoo/addons/l10n_es_aeat_mod111/i18n/ca.po
odoo/addons/l10n_es_aeat_mod111/i18n/cs.po
odoo/addons/l10n_es_aeat_mod111/i18n/de.po
odoo/addons/l10n_es_aeat_mod111/i18n/es.po
odoo/addons/l10n_es_aeat_mod111/i18n/es_CO.po
odoo/addons/l10n_es_aeat_mod111/i18n/es_CR.po
odoo/addons/l10n_es_aeat_mod111/i18n/eu.po
odoo/addons/l10n_es_aeat_mod111/i18n/fr.po
odoo/addons/l10n_es_aeat_mod111/i18n/gl.po
odoo/addons/l10n_es_aeat_mod111/i18n/hr.po
odoo/addons/l10n_es_aeat_mod111/i18n/l10n_es_aeat_mod111.pot
odoo/addons/l10n_es_aeat_mod111/i18n/nl.po
odoo/addons/l10n_es_aeat_mod111/i18n/pl.po
odoo/addons/l10n_es_aeat_mod111/i18n/pt.po
odoo/addons/l10n_es_aeat_mod111/i18n/pt_BR.po
odoo/addons/l10n_es_aeat_mod111/i18n/ru.po
odoo/addons/l10n_es_aeat_mod111/i18n/sl.po
odoo/addons/l10n_es_aeat_mod111/i18n/sv.po
odoo/addons/l10n_es_aeat_mod111/i18n/tr.po
odoo/addons/l10n_es_aeat_mod111/i18n/vi.po
odoo/addons/l10n_es_aeat_mod111/models/__init__.py
odoo/addons/l10n_es_aeat_mod111/models/mod111.py
odoo/addons/l10n_es_aeat_mod111/readme/CONTRIBUTORS.md
odoo/addons/l10n_es_aeat_mod111/readme/DESCRIPTION.md
odoo/addons/l10n_es_aeat_mod111/readme/ROADMAP.md
odoo/addons/l10n_es_aeat_mod111/readme/USAGE.md
odoo/addons/l10n_es_aeat_mod111/security/ir.model.access.csv
odoo/addons/l10n_es_aeat_mod111/security/l10n_es_aeat_mod111_security.xml
odoo/addons/l10n_es_aeat_mod111/static/description/icon.png
odoo/addons/l10n_es_aeat_mod111/static/description/icon_source.svg
odoo_addon_l10n_es_aeat_mod111-18.0.1.0.4.1.dist-info/METADATA
odoo_addon_l10n_es_aeat_mod111-18.0.1.0.4.1.dist-info/WHEEL
odoo_addon_l10n_es_aeat_mod111-18.0.1.0.4.1.dist-info/top_level.txt
odoo_addon_l10n_es_aeat_mod111-18.0.1.0.4.1.dist-info/RECORD
